mopidy_mqtt/__init__.py
mopidy_mqtt/ext.conf
mopidy_mqtt/frontend.py
mopidy_mqtt/mqtt.py
mopidy_mqtt/utils.py
Mopidy_MQTT_NG-1.0.0.dist-info/LICENSE
Mopidy_MQTT_NG-1.0.0.dist-info/METADATA
Mopidy_MQTT_NG-1.0.0.dist-info/WHEEL
Mopidy_MQTT_NG-1.0.0.dist-info/entry_points.txt
Mopidy_MQTT_NG-1.0.0.dist-info/top_level.txt
Mopidy_MQTT_NG-1.0.0.dist-info/RECORD
