Metadata-Version: 2.1
Name: Mopidy-MQTT-NG
Version: 1.0.0
Summary: Mopidy extension for remote control via MQTT broker
Home-page: https://github.com/odiroot/mopidy-mqtt
Author: Michal Odnous
Author-email: odiroot@users.noreply.github.com
License: Apache License, Version 2.0
Platform: UNKNOWN
Classifier: Development Status :: 5 - Production/Stable
Classifier: Intended Audience :: End Users/Desktop
Classifier: License :: OSI Approved :: Apache Software License
Classifier: Operating System :: OS Independent
Classifier: Programming Language :: Python
Classifier: Programming Language :: Python :: 3
Classifier: Programming Language :: Python :: 3.7
Classifier: Topic :: Multimedia :: Sound/Audio :: Players
Classifier: Environment :: No Input/Output (Daemon)
Requires-Dist: Mopidy (>=3.0)
Requires-Dist: paho-mqtt
Requires-Dist: Pykka (>=2.0)
Requires-Dist: setuptools
